setup.cfg
setup.py
pocketwsgi/__init__.py
pocketwsgi.egg-info/PKG-INFO
pocketwsgi.egg-info/SOURCES.txt
pocketwsgi.egg-info/dependency_links.txt
pocketwsgi.egg-info/entry_points.txt
pocketwsgi.egg-info/not-zip-safe
pocketwsgi.egg-info/paster_plugins.txt
pocketwsgi.egg-info/requires.txt
pocketwsgi.egg-info/top_level.txt
