Metadata-Version: 1.0
Name: pocketwsgi
Version: 0.2.1
Summary: tiny wsgi application framework
Home-page: http://aodagx.ddo.jp/aodag/projects/pocketwsgi
Author: Atsushi Odagiri
Author-email: aodagx@gmail.com
License: UNKNOWN
Keywords: wsgi
Platform: UNKNOWN
Classifier: Topic :: Internet :: WWW/HTTP :: WSGI
